{
  "project_info": {
    "project_number": "680714216984",
    "firebase_url": "https://dchelper-48256-default-rtdb.firebaseio.com",
    "project_id": "dchelper-48256",
    "storage_bucket": "dchelper-48256.appspot.com"
  },
  "client": [
    {
      "client_info": {
        "mobilesdk_app_id": "1:680714216984:android:e05c243f91a3c944cc856d",
        "android_client_info": {
          "package_name": "com.example.dchelper"
        }
      },
      "oauth_client": [
        {
          "client_id": "680714216984-uh2gjvlctd30kksamd90b9uokt6pq3ea.apps.googleusercontent.com",
          "client_type": 1,
          "android_info": {
            "package_name": "com.example.dchelper",
            "certificate_hash": "9bebeb7d324582fb036bc46131e30e3e0d7688c8"
          }
        },
        {
          "client_id": "680714216984-iffgvdnbrpjdtu9vuud2idntofmk35e2.apps.googleusercontent.com",
          "client_type": 3
        }
      ],
      "api_key": [
        {
          "current_key": "AIzaSyBxcW5h0sHRWye7_abW-ls5e2gHd_pyblM"
        }
      ],
      "services": {
        "appinvite_service": {
          "other_platform_oauth_client": [
            {
              "client_id": "680714216984-iffgvdnbrpjdtu9vuud2idntofmk35e2.apps.googleusercontent.com",
              "client_type": 3
            }
          ]
        }
      }
    }
  ],
  "configuration_version": "1"
}